setiastro/__init__.py
setiastro/data/catalogs/astrobin_filters.csv
setiastro/data/catalogs/astrobin_filters_page1_local.csv
setiastro/data/catalogs/cali2.csv
setiastro/data/catalogs/cali2color.csv
setiastro/data/catalogs/celestial_catalog - original.csv
setiastro/data/catalogs/celestial_catalog.csv
setiastro/data/catalogs/detected_stars.csv
setiastro/data/catalogs/fits_header_data.csv
setiastro/data/catalogs/List_of_Galaxies_with_Distances_Gly.csv
setiastro/data/catalogs/test.csv
setiastro/data/catalogs/updated_celestial_catalog.csv
setiastro/data/SASP_data.fits
setiastro/images/3dplanet.png
setiastro/images/abeicon.png
setiastro/images/abeicon.svg
setiastro/images/aberration.png
setiastro/images/acv_icon.png
setiastro/images/andromedatry.png
setiastro/images/andromedatry_satellited.png
setiastro/images/annotated.png
setiastro/images/aperture.png
setiastro/images/Astro_Spikes.png
setiastro/images/astrosuite.ico
setiastro/images/astrosuite.png
setiastro/images/astrosuitepro.icns
setiastro/images/astrosuitepro.ico
setiastro/images/astrosuitepro.png
setiastro/images/background.png
setiastro/images/background2.png
setiastro/images/Background_startup.jpg
setiastro/images/benchmark.png
setiastro/images/big_moon_stabilizer_timeline.png
setiastro/images/big_moon_stabilizer_timeline_clean.png
setiastro/images/blaster.png
setiastro/images/blink.png
setiastro/images/clahe.png
setiastro/images/clonestamp.png
setiastro/images/collage.png
setiastro/images/colorwheel.png
setiastro/images/colorwheel.svg
setiastro/images/contsub.png
setiastro/images/convo.png
setiastro/images/copyslot.png
setiastro/images/cosmic.png
setiastro/images/cosmic.svg
setiastro/images/cosmicsat.png
setiastro/images/cosmicsat.svg
setiastro/images/crop1.png
setiastro/images/cropicon.png
setiastro/images/curves.png
setiastro/images/cvs.png
setiastro/images/debayer.png
setiastro/images/denoise_cnn_custom.png
setiastro/images/denoise_cnn_graph.png
setiastro/images/disk.png
setiastro/images/dse.png
setiastrosuitepro-1.8.3.post2.dist-info/entry_points.txt
setiastrosuitepro-1.8.3.post2.dist-info/licenses/LICENSE
setiastrosuitepro-1.8.3.post2.dist-info/licenses/license.txt
setiastrosuitepro-1.8.3.post2.dist-info/METADATA
setiastrosuitepro-1.8.3.post2.dist-info/WHEEL
setiastrosuitepro-1.8.3.post2.dist-info/RECORD
