Metadata-Version: 2.4
Name: setiastrosuitepro
Version: 1.8.3.post2
Summary: Seti Astro Suite Pro - Advanced astrophotography toolkit for image calibration, stacking, registration, photometry, and visualization
License: GPL-3.0
License-File: LICENSE
License-File: license.txt
Keywords: astrophotography,astronomy,image-processing,photometry
Author: Franklin Marek
Author-email: info@setiastro.com
Requires-Python: >=3.10,<4.0
Classifier: Development Status :: 4 - Beta
Classifier: Intended Audience :: Science/Research
Classifier: License :: OSI Approved :: GNU General Public License v3 (GPLv3)
Classifier: Programming Language :: Python :: 3
Classifier: Programming Language :: Python :: 3.10
Classifier: Programming Language :: Python :: 3.11
Classifier: Programming Language :: Python :: 3.12
Classifier: Programming Language :: Python :: 3.13
Classifier: Programming Language :: Python :: 3.14
Classifier: Topic :: Scientific/Engineering :: Astronomy
Requires-Dist: Pillow
Requires-Dist: PyQt6
Requires-Dist: astroalign
Requires-Dist: astropy
Requires-Dist: astroquery
Requires-Dist: exifread
Requires-Dist: imagecodecs (>=2025.11.11,<2026.0.0) ; python_version >= "3.11" and sys_platform == "darwin"
Requires-Dist: imageio
Requires-Dist: jplephem
Requires-Dist: lightkurve
Requires-Dist: lz4
Requires-Dist: matplotlib
Requires-Dist: numba
Requires-Dist: numpy
Requires-Dist: oktopus
Requires-Dist: onnx
Requires-Dist: onnxruntime ; sys_platform != "linux" and sys_platform != "win32"
Requires-Dist: onnxruntime-directml ; sys_platform == "win32"
Requires-Dist: onnxruntime-gpu ; sys_platform == "linux"
Requires-Dist: opencv-python-headless
Requires-Dist: pandas
Requires-Dist: photutils
Requires-Dist: plotly
Requires-Dist: psutil
Requires-Dist: py-cpuinfo
Requires-Dist: pyqtgraph
Requires-Dist: pytz
Requires-Dist: pywavelets
Requires-Dist: rawpy
Requires-Dist: reproject
Requires-Dist: requests
Requires-Dist: scipy
Requires-Dist: sep
Requires-Dist: skyfield
Requires-Dist: tifffile
Requires-Dist: tzlocal
Requires-Dist: xisf
Requires-Dist: zstandard
Project-URL: Homepage, https://www.setiastro.com
Project-URL: Repository, https://github.com/setiastro/setiastrosuitepro
